optimaimg-0.7.1.dist-info/METADATA
optimaimg-0.7.1.dist-info/WHEEL
optimaimg-0.7.1.dist-info/entry_points.txt
optimaimg-0.7.1.dist-info/license_files/LICENSE
cli/cli.py
optimaimg/__init__.py
optimaimg/optimaimg.cpython-37m-x86_64-linux-gnu.so
optimaimg-0.7.1.dist-info/RECORD
